catimerge/__init__.py
catimerge/py.typed
catimerge-0.1.1.dist-info/LICENSE.AGPLv3
catimerge-0.1.1.dist-info/METADATA
catimerge-0.1.1.dist-info/WHEEL
catimerge-0.1.1.dist-info/entry_points.txt
catimerge-0.1.1.dist-info/top_level.txt
catimerge-0.1.1.dist-info/RECORD
